pyLong/__init__.py
pyLong/annotations/annotation.py
pyLong/annotations/arc.py
pyLong/annotations/horizontal_annotation.py
pyLong/annotations/interval.py
pyLong/annotations/line.py
pyLong/annotations/polygon.py
pyLong/annotations/rectangle.py
pyLong/annotations/text.py
pyLong/annotations/vertical_annotation.py
pyLong/dictionnaries/colors.py
pyLong/dictionnaries/legend.py
pyLong/dictionnaries/styles.py
pyLong/layouts/grid.py
pyLong/layouts/layout.py
pyLong/layouts/legend.py
pyLong/layouts/s_axis.py
pyLong/layouts/sublayout.py
pyLong/layouts/x_axis.py
pyLong/layouts/y_axis.py
pyLong/layouts/z_axis.py
pyLong/lists/alignments.py
pyLong/lists/arrows.py
pyLong/lists/fonts.py
pyLong/lists/hatches.py
pyLong/misc/duration.py
pyLong/misc/intersect.py
pyLong/profiles/sprofile.py
pyLong/profiles/yprofile.py
pyLong/profiles/zprofile.py
pyLong/toolbox/corominas.py
pyLong/toolbox/energy_line.py
pyLong/toolbox/evofond/granulometry.py
pyLong/toolbox/evofond/hydrograph.py
pyLong/toolbox/flow_r.py
pyLong/toolbox/mezap.py
pyLong/toolbox/platrock2d_shape_viewer.py
pyLong/toolbox/platrock2d_viewer.py
pyLong/toolbox/rickenmann.py
long_profile-1.0.0.dist-info/LICENSE
long_profile-1.0.0.dist-info/METADATA
long_profile-1.0.0.dist-info/WHEEL
long_profile-1.0.0.dist-info/RECORD
